<?xml version="1.0" encoding="UTF-8"?>
<root>
  <annotation type="1">
    <metadata>
      <id>0</id>
      <auteur>Reference</auteur>
      <date>14/10/14 19:22</date>
      <document>Lieu-dit.html</document>
    </metadata>
    <SE>
      <id>0</id>
      <text>Appellatifs géographiques ou topographiques
les Bel-Air, Beausoleil sont nombreux en métropole ;
le Bout du Monde, à Sixt-Fer-à-Cheval ;
la Clarté (à Perros-Guirec) ;
l'Oubliette (Maine-et-Loire) ;
le Val du Puits ;
Groenendael (Belgique) appellatif toponymique flamand dael « vallée » précédé de l'adjectif de couleur signifiant « verte »;
Sept Fontaines (Belgique) ;
le Bosquet ;
la Mare.</text>
      <span begin="1061" end="1451" />
    </SE>
    <comment>Consensus</comment>
  </annotation>
  <annotation type="1">
    <metadata>
      <id>1</id>
      <auteur>Autre</auteur>
      <date>3/01/14 17:47</date>
      <document>Lieu-dit.html</document>
    </metadata>
    <SE>
      <id>1</id>
      <text>Appellatifs liés à une activité humaine ou à la propriété
les Hautes Granges ;
les Closeries ;
la Vénerie.</text>
      <span begin="1452" end="1558" />
    </SE>
    <comment />
  </annotation>
  <annotation type="1">
    <metadata>
      <id>2</id>
      <auteur>Autre</auteur>
      <date>3/01/14 17:48</date>
      <document>Lieu-dit.html</document>
    </metadata>
    <SE>
      <id>2</id>
      <text>Appellatifs (topographiques, floraux ou type d'habitat) et noms de personnes
Chez-Billard-Haut (Charente), Chez Gruel (Charente, Saint-Martial-de-Mirambeau), Chez-Maurice (Haute-Savoie), de chez « maison » (du latin casa) + nom de personne ;
la Girardière du nom de famille Girard + suffixe -ière (à partir du Moyen Âge), les Grandes Châtelaines
Kertanguy (Basse-Bretagne), du breton ker « maison, village » + Tanguy nom de personne ;
Saint-Aubin-des-Chaumes, Saint-Brisson, etc. (formations médiévales en Saint-, généralement d'anciennes paroisses) ;
la Ville Hamon, la Ville Juhel, etc. (formations toponymiques médiévales où ville a encore son sens de « groupe d'habitations »);
le ''Parc des Princes'' de Boulogne-Billancourt
Carrefour Léonard, dans la forêt de Soignes (Bruxelles)
Bois Joly (Ile-d'Aix) ;
Moncourt, nom d'une ancienne paroisse, toponyme médiéval en -court, précédé d'un nom de personne germanique.</text>
      <span begin="1559" end="2477" />
    </SE>
    <comment />
  </annotation>
  <annotation type="1">
    <metadata>
      <id>3</id>
      <auteur>Autre</auteur>
      <date>3/01/14 17:49</date>
      <document>Lieu-dit.html</document>
    </metadata>
    <SE>
      <id>3</id>
      <text>Appellations à caractère anecdotique, historique ou mythique
le Camp de César ;
la Mi-Voie ;
le Saut des Français (en Duranus) ;
l'Ermite (Belgique);
Passe-tout-Outre, à la frontière franco-belge (Autreppe).</text>
      <span begin="2478" end="2685" />
    </SE>
    <comment />
  </annotation>
  <annotation type="2">
    <metadata>
      <id>0</id>
      <auteur>Reference</auteur>
      <date>14/10/14 19:22</date>
      <document>Lieu-dit.html</document>
    </metadata>
    <SEval type="primer_syntax" idSE="0" />
  </annotation>
  <annotation type="2">
    <metadata>
      <id>0</id>
      <auteur>Reference</auteur>
      <date>14/10/14 19:22</date>
      <document>Lieu-dit.html</document>
    </metadata>
    <SEval type="items_syntax" idSE="0">
      <item id="0" />
      <item id="1" />
      <item id="2" />
      <item id="3" />
      <item id="4" />
      <item id="5" />
      <item id="6" />
      <item id="7" />
      <item id="8" />
    </SEval>
  </annotation>
  <annotation type="2">
    <metadata>
      <id>1</id>
      <auteur>Autre</auteur>
      <date>3/01/14 17:47</date>
      <document>Lieu-dit.html</document>
    </metadata>
    <SEval type="primer_syntax" idSE="1" />
  </annotation>
  <annotation type="2">
    <metadata>
      <id>1</id>
      <auteur>Autre</auteur>
      <date>3/01/14 17:47</date>
      <document>Lieu-dit.html</document>
    </metadata>
    <SEval type="items_syntax" idSE="1">
      <item id="0" />
      <item id="1" />
      <item id="2" />
    </SEval>
  </annotation>
  <annotation type="2">
    <metadata>
      <id>2</id>
      <auteur>Autre</auteur>
      <date>3/01/14 17:48</date>
      <document>Lieu-dit.html</document>
    </metadata>
    <SEval type="primer_syntax" idSE="2" />
  </annotation>
  <annotation type="2">
    <metadata>
      <id>2</id>
      <auteur>Autre</auteur>
      <date>3/01/14 17:48</date>
      <document>Lieu-dit.html</document>
    </metadata>
    <SEval type="items_syntax" idSE="2">
      <item id="0" />
      <item id="1" />
      <item id="2" />
      <item id="3" />
      <item id="4" />
      <item id="5" />
      <item id="6" />
      <item id="7" />
      <item id="8" />
    </SEval>
  </annotation>
  <annotation type="2">
    <metadata>
      <id>3</id>
      <auteur>Autre</auteur>
      <date>3/01/14 17:49</date>
      <document>Lieu-dit.html</document>
    </metadata>
    <SEval type="primer_syntax" idSE="3" />
  </annotation>
  <annotation type="2">
    <metadata>
      <id>3</id>
      <auteur>Autre</auteur>
      <date>3/01/14 17:49</date>
      <document>Lieu-dit.html</document>
    </metadata>
    <SEval type="items_syntax" idSE="3">
      <item id="0" />
      <item id="1" />
      <item id="2" />
      <item id="3" />
      <item id="4" />
    </SEval>
  </annotation>
  <annotation type="2">
    <metadata>
      <id>0</id>
      <auteur>Reference</auteur>
      <date>14/10/14 19:22</date>
      <document>Lieu-dit.html</document>
    </metadata>
    <SEval type="primer" idSE="0">
      <span begin="1" end="44" />
      <text>Appellatifs géographiques ou topographiques</text>
    </SEval>
  </annotation>
  <annotation type="2">
    <metadata>
      <id>0</id>
      <auteur>Reference</auteur>
      <date>14/10/14 19:22</date>
      <document>Lieu-dit.html</document>
    </metadata>
    <SEval type="items" idSE="0">
      <span begin="45" end="97" id="0" />
      <text id="0">les Bel-Air, Beausoleil sont nombreux en métropole ;</text>
      <span begin="98" end="137" id="1" />
      <text id="1">le Bout du Monde, à Sixt-Fer-à-Cheval ;</text>
      <span begin="138" end="167" id="2" />
      <text id="2">la Clarté (à Perros-Guirec) ;</text>
      <span begin="168" end="198" id="3" />
      <text id="3">l'Oubliette (Maine-et-Loire) ;</text>
      <span begin="199" end="216" id="4" />
      <text id="4">le Val du Puits ;</text>
      <span begin="217" end="341" id="5" />
      <text id="5">Groenendael (Belgique) appellatif toponymique flamand dael « vallée » précédé de l'adjectif de couleur signifiant « verte »;</text>
      <span begin="342" end="369" id="6" />
      <text id="6">Sept Fontaines (Belgique) ;</text>
      <span begin="370" end="382" id="7" />
      <text id="7">le Bosquet ;</text>
      <span begin="383" end="391" id="8" />
      <text id="8">la Mare.</text>
    </SEval>
  </annotation>
  <annotation type="2">
    <metadata>
      <id>1</id>
      <auteur>Autre</auteur>
      <date>3/01/14 17:47</date>
      <document>Lieu-dit.html</document>
    </metadata>
    <SEval type="primer" idSE="1">
      <span begin="1" end="58" />
      <text>Appellatifs liés à une activité humaine ou à la propriété</text>
    </SEval>
  </annotation>
  <annotation type="2">
    <metadata>
      <id>1</id>
      <auteur>Autre</auteur>
      <date>3/01/14 17:47</date>
      <document>Lieu-dit.html</document>
    </metadata>
    <SEval type="items" idSE="1">
      <span begin="59" end="79" id="0" />
      <text id="0">les Hautes Granges ;</text>
      <span begin="80" end="95" id="1" />
      <text id="1">les Closeries ;</text>
      <span begin="96" end="107" id="2" />
      <text id="2">la Vénerie.</text>
    </SEval>
  </annotation>
  <annotation type="2">
    <metadata>
      <id>2</id>
      <auteur>Autre</auteur>
      <date>3/01/14 17:48</date>
      <document>Lieu-dit.html</document>
    </metadata>
    <SEval type="primer" idSE="2">
      <span begin="1" end="77" />
      <text>Appellatifs (topographiques, floraux ou type d'habitat) et noms de personnes</text>
    </SEval>
  </annotation>
  <annotation type="2">
    <metadata>
      <id>2</id>
      <auteur>Autre</auteur>
      <date>3/01/14 17:48</date>
      <document>Lieu-dit.html</document>
    </metadata>
    <SEval type="items" idSE="2">
      <span begin="78" end="242" id="0" />
      <text id="0">Chez-Billard-Haut (Charente), Chez Gruel (Charente, Saint-Martial-de-Mirambeau), Chez-Maurice (Haute-Savoie), de chez « maison » (du latin casa) + nom de personne ;</text>
      <span begin="243" end="346" id="1" />
      <text id="1">la Girardière du nom de famille Girard + suffixe -ière (à partir du Moyen Âge), les Grandes Châtelaines</text>
      <span begin="347" end="435" id="2" />
      <text id="2">Kertanguy (Basse-Bretagne), du breton ker « maison, village » + Tanguy nom de personne ;</text>
      <span begin="436" end="552" id="3" />
      <text id="3">Saint-Aubin-des-Chaumes, Saint-Brisson, etc. (formations médiévales en Saint-, généralement d'anciennes paroisses) ;</text>
      <span begin="553" end="682" id="4" />
      <text id="4">la Ville Hamon, la Ville Juhel, etc. (formations toponymiques médiévales où ville a encore son sens de « groupe d'habitations »);</text>
      <span begin="683" end="730" id="5" />
      <text id="5">le ''Parc des Princes'' de Boulogne-Billancourt</text>
      <span begin="731" end="786" id="6" />
      <text id="6">Carrefour Léonard, dans la forêt de Soignes (Bruxelles)</text>
      <span begin="787" end="810" id="7" />
      <text id="7">Bois Joly (Ile-d'Aix) ;</text>
      <span begin="811" end="919" id="8" />
      <text id="8">Moncourt, nom d'une ancienne paroisse, toponyme médiéval en -court, précédé d'un nom de personne germanique.</text>
    </SEval>
  </annotation>
  <annotation type="2">
    <metadata>
      <id>3</id>
      <auteur>Autre</auteur>
      <date>3/01/14 17:49</date>
      <document>Lieu-dit.html</document>
    </metadata>
    <SEval type="primer" idSE="3">
      <span begin="1" end="61" />
      <text>Appellations à caractère anecdotique, historique ou mythique</text>
    </SEval>
  </annotation>
  <annotation type="2">
    <metadata>
      <id>3</id>
      <auteur>Autre</auteur>
      <date>3/01/14 17:49</date>
      <document>Lieu-dit.html</document>
    </metadata>
    <SEval type="items" idSE="3">
      <span begin="62" end="80" id="0" />
      <text id="0">le Camp de César ;</text>
      <span begin="81" end="93" id="1" />
      <text id="1">la Mi-Voie ;</text>
      <span begin="94" end="129" id="2" />
      <text id="2">le Saut des Français (en Duranus) ;</text>
      <span begin="130" end="150" id="3" />
      <text id="3">l'Ermite (Belgique);</text>
      <span begin="151" end="208" id="4" />
      <text id="4">Passe-tout-Outre, à la frontière franco-belge (Autreppe).</text>
    </SEval>
  </annotation>
  <annotation type="2">
    <metadata>
      <id>0</id>
      <auteur>Reference</auteur>
      <date>14/10/14 19:22</date>
      <document>Lieu-dit.html</document>
    </metadata>
    <SEval type="concept" idSE="0" localisation="primer" idItem="-1">
      <span begin="1" end="44" id="0" />
      <text id="0">Appellatifs géographiques ou topographiques</text>
    </SEval>
  </annotation>
  <annotation type="2">
    <metadata>
      <id>0</id>
      <auteur>Reference</auteur>
      <date>14/10/14 19:22</date>
      <document>Lieu-dit.html</document>
    </metadata>
    <SEval type="concept" idSE="0" localisation="item" idItem="0">
      <span begin="48" end="56" id="0" />
      <text id="0">Bel-Air</text>
      <span begin="58" end="68" id="1" />
      <text id="1">Beausoleil</text>
    </SEval>
  </annotation>
  <annotation type="2">
    <metadata>
      <id>0</id>
      <auteur>Reference</auteur>
      <date>14/10/14 19:22</date>
      <document>Lieu-dit.html</document>
    </metadata>
    <SEval type="concept" idSE="0" localisation="item" idItem="1">
      <span begin="98" end="114" id="0" />
      <text id="0">le Bout du Monde</text>
    </SEval>
  </annotation>
  <annotation type="2">
    <metadata>
      <id>0</id>
      <auteur>Reference</auteur>
      <date>14/10/14 19:22</date>
      <document>Lieu-dit.html</document>
    </metadata>
    <SEval type="concept" idSE="0" localisation="item" idItem="2">
      <span begin="138" end="147" id="0" />
      <text id="0">la Clarté</text>
    </SEval>
  </annotation>
  <annotation type="2">
    <metadata>
      <id>0</id>
      <auteur>Reference</auteur>
      <date>14/10/14 19:22</date>
      <document>Lieu-dit.html</document>
    </metadata>
    <SEval type="concept" idSE="0" localisation="item" idItem="3">
      <span begin="168" end="180" id="0" />
      <text id="0">l'Oubliette</text>
    </SEval>
  </annotation>
  <annotation type="2">
    <metadata>
      <id>0</id>
      <auteur>Reference</auteur>
      <date>14/10/14 19:22</date>
      <document>Lieu-dit.html</document>
    </metadata>
    <SEval type="concept" idSE="0" localisation="item" idItem="4">
      <span begin="199" end="214" id="0" />
      <text id="0">le Val du Puits</text>
    </SEval>
  </annotation>
  <annotation type="2">
    <metadata>
      <id>0</id>
      <auteur>Reference</auteur>
      <date>14/10/14 19:22</date>
      <document>Lieu-dit.html</document>
    </metadata>
    <SEval type="concept" idSE="0" localisation="item" idItem="5">
      <span begin="217" end="229" id="0" />
      <text id="0">Groenendael</text>
    </SEval>
  </annotation>
  <annotation type="2">
    <metadata>
      <id>0</id>
      <auteur>Reference</auteur>
      <date>14/10/14 19:22</date>
      <document>Lieu-dit.html</document>
    </metadata>
    <SEval type="concept" idSE="0" localisation="item" idItem="6">
      <span begin="342" end="356" id="0" />
      <text id="0">Sept Fontaines</text>
    </SEval>
  </annotation>
  <annotation type="2">
    <metadata>
      <id>0</id>
      <auteur>Reference</auteur>
      <date>14/10/14 19:22</date>
      <document>Lieu-dit.html</document>
    </metadata>
    <SEval type="concept" idSE="0" localisation="item" idItem="7">
      <span begin="370" end="381" id="0" />
      <text id="0">le Bosquet</text>
    </SEval>
  </annotation>
  <annotation type="2">
    <metadata>
      <id>0</id>
      <auteur>Reference</auteur>
      <date>14/10/14 19:22</date>
      <document>Lieu-dit.html</document>
    </metadata>
    <SEval type="concept" idSE="0" localisation="item" idItem="8">
      <span begin="383" end="390" id="0" />
      <text id="0">la Mare</text>
    </SEval>
  </annotation>
  <annotation type="2">
    <metadata>
      <id>1</id>
      <auteur>Autre</auteur>
      <date>3/01/14 17:47</date>
      <document>Lieu-dit.html</document>
    </metadata>
    <SEval type="concept" idSE="1" localisation="primer" idItem="-1">
      <span begin="1" end="40" id="0" />
      <text id="0">Appellatifs liés à une activité humaine</text>
    </SEval>
  </annotation>
  <annotation type="2">
    <metadata>
      <id>1</id>
      <auteur>Autre</auteur>
      <date>3/01/14 17:47</date>
      <document>Lieu-dit.html</document>
    </metadata>
    <SEval type="concept" idSE="1" localisation="item" idItem="0">
      <span begin="59" end="77" id="0" />
      <text id="0">les Hautes Granges</text>
    </SEval>
  </annotation>
  <annotation type="2">
    <metadata>
      <id>1</id>
      <auteur>Autre</auteur>
      <date>3/01/14 17:47</date>
      <document>Lieu-dit.html</document>
    </metadata>
    <SEval type="concept" idSE="1" localisation="item" idItem="1">
      <span begin="80" end="93" id="0" />
      <text id="0">les Closeries</text>
    </SEval>
  </annotation>
  <annotation type="2">
    <metadata>
      <id>1</id>
      <auteur>Autre</auteur>
      <date>3/01/14 17:47</date>
      <document>Lieu-dit.html</document>
    </metadata>
    <SEval type="concept" idSE="1" localisation="item" idItem="2">
      <span begin="96" end="106" id="0" />
      <text id="0">la Vénerie</text>
    </SEval>
  </annotation>
  <annotation type="2">
    <metadata>
      <id>2</id>
      <auteur>Autre</auteur>
      <date>3/01/14 17:48</date>
      <document>Lieu-dit.html</document>
    </metadata>
    <SEval type="concept" idSE="2" localisation="primer" idItem="-1">
      <span begin="1" end="12" id="0" />
      <text id="0">Appellatifs</text>
      <span begin="60" end="77" id="1" />
      <text id="1">noms de personnes</text>
    </SEval>
  </annotation>
  <annotation type="2">
    <metadata>
      <id>2</id>
      <auteur>Autre</auteur>
      <date>3/01/14 17:48</date>
      <document>Lieu-dit.html</document>
    </metadata>
    <SEval type="concept" idSE="2" localisation="item" idItem="0">
      <span begin="78" end="95" id="0" />
      <text id="0">Chez-Billard-Haut</text>
    </SEval>
  </annotation>
  <annotation type="2">
    <metadata>
      <id>2</id>
      <auteur>Autre</auteur>
      <date>3/01/14 17:48</date>
      <document>Lieu-dit.html</document>
    </metadata>
    <SEval type="concept" idSE="2" localisation="item" idItem="1">
      <span begin="243" end="256" id="0" />
      <text id="0">la Girardière</text>
    </SEval>
  </annotation>
  <annotation type="2">
    <metadata>
      <id>2</id>
      <auteur>Autre</auteur>
      <date>3/01/14 17:48</date>
      <document>Lieu-dit.html</document>
    </metadata>
    <SEval type="concept" idSE="2" localisation="item" idItem="2">
      <span begin="347" end="356" id="0" />
      <text id="0">Kertanguy</text>
    </SEval>
  </annotation>
  <annotation type="2">
    <metadata>
      <id>2</id>
      <auteur>Autre</auteur>
      <date>3/01/14 17:48</date>
      <document>Lieu-dit.html</document>
    </metadata>
    <SEval type="concept" idSE="2" localisation="item" idItem="3">
      <span begin="436" end="459" id="0" />
      <text id="0">Saint-Aubin-des-Chaumes</text>
    </SEval>
  </annotation>
  <annotation type="2">
    <metadata>
      <id>2</id>
      <auteur>Autre</auteur>
      <date>3/01/14 17:48</date>
      <document>Lieu-dit.html</document>
    </metadata>
    <SEval type="concept" idSE="2" localisation="item" idItem="4">
      <span begin="553" end="567" id="0" />
      <text id="0">la Ville Hamon</text>
      <span begin="568" end="583" id="1" />
      <text id="1">la Ville Juhel</text>
    </SEval>
  </annotation>
  <annotation type="2">
    <metadata>
      <id>2</id>
      <auteur>Autre</auteur>
      <date>3/01/14 17:48</date>
      <document>Lieu-dit.html</document>
    </metadata>
    <SEval type="concept" idSE="2" localisation="item" idItem="5">
      <span begin="683" end="707" id="0" />
      <text id="0">le ''Parc des Princes''</text>
    </SEval>
  </annotation>
  <annotation type="2">
    <metadata>
      <id>2</id>
      <auteur>Autre</auteur>
      <date>3/01/14 17:48</date>
      <document>Lieu-dit.html</document>
    </metadata>
    <SEval type="concept" idSE="2" localisation="item" idItem="6">
      <span begin="731" end="748" id="0" />
      <text id="0">Carrefour Léonard</text>
    </SEval>
  </annotation>
  <annotation type="2">
    <metadata>
      <id>2</id>
      <auteur>Autre</auteur>
      <date>3/01/14 17:48</date>
      <document>Lieu-dit.html</document>
    </metadata>
    <SEval type="concept" idSE="2" localisation="item" idItem="7">
      <span begin="787" end="796" id="0" />
      <text id="0">Bois Joly</text>
    </SEval>
  </annotation>
  <annotation type="2">
    <metadata>
      <id>2</id>
      <auteur>Autre</auteur>
      <date>3/01/14 17:48</date>
      <document>Lieu-dit.html</document>
    </metadata>
    <SEval type="concept" idSE="2" localisation="item" idItem="8">
      <span begin="811" end="819" id="0" />
      <text id="0">Moncourt</text>
    </SEval>
  </annotation>
  <annotation type="2">
    <metadata>
      <id>3</id>
      <auteur>Autre</auteur>
      <date>3/01/14 17:49</date>
      <document>Lieu-dit.html</document>
    </metadata>
    <SEval type="concept" idSE="3" localisation="primer" idItem="-1">
      <span begin="1" end="37" id="0" />
      <text id="0">Appellations à caractère anecdotique</text>
    </SEval>
  </annotation>
  <annotation type="2">
    <metadata>
      <id>3</id>
      <auteur>Autre</auteur>
      <date>3/01/14 17:49</date>
      <document>Lieu-dit.html</document>
    </metadata>
    <SEval type="concept" idSE="3" localisation="item" idItem="0">
      <span begin="62" end="78" id="0" />
      <text id="0">le Camp de César</text>
    </SEval>
  </annotation>
  <annotation type="2">
    <metadata>
      <id>3</id>
      <auteur>Autre</auteur>
      <date>3/01/14 17:49</date>
      <document>Lieu-dit.html</document>
    </metadata>
    <SEval type="concept" idSE="3" localisation="item" idItem="1">
      <span begin="81" end="91" id="0" />
      <text id="0">la Mi-Voie</text>
    </SEval>
  </annotation>
  <annotation type="2">
    <metadata>
      <id>3</id>
      <auteur>Autre</auteur>
      <date>3/01/14 17:49</date>
      <document>Lieu-dit.html</document>
    </metadata>
    <SEval type="concept" idSE="3" localisation="item" idItem="2">
      <span begin="94" end="114" id="0" />
      <text id="0">le Saut des Français</text>
    </SEval>
  </annotation>
  <annotation type="2">
    <metadata>
      <id>3</id>
      <auteur>Autre</auteur>
      <date>3/01/14 17:49</date>
      <document>Lieu-dit.html</document>
    </metadata>
    <SEval type="concept" idSE="3" localisation="item" idItem="3">
      <span begin="130" end="138" id="0" />
      <text id="0">l'Ermite</text>
    </SEval>
  </annotation>
  <annotation type="2">
    <metadata>
      <id>3</id>
      <auteur>Autre</auteur>
      <date>3/01/14 17:49</date>
      <document>Lieu-dit.html</document>
    </metadata>
    <SEval type="concept" idSE="3" localisation="item" idItem="4">
      <span begin="151" end="167" id="0" />
      <text id="0">Passe-tout-Outre</text>
    </SEval>
  </annotation>
  <annotation type="2">
    <metadata>
      <id>0</id>
      <auteur>Reference</auteur>
      <date>14/10/14 19:22</date>
      <document>Lieu-dit.html</document>
    </metadata>
    <SEval type="axe_visuel" idSE="0">
      <horizontale value="0" />
      <verticale value="1" />
      <navigationnelle value="0" />
      <hypertextuelle value="1" />
    </SEval>
  </annotation>
  <annotation type="2">
    <metadata>
      <id>0</id>
      <auteur>Reference</auteur>
      <date>14/10/14 19:22</date>
      <document>Lieu-dit.html</document>
    </metadata>
    <SEval type="axe_rhetorique" idSE="0">
      <paradigmatique value="1" />
      <syntagmatique value="0" />
      <hybride value="0" />
      <bivalente value="0" />
    </SEval>
  </annotation>
  <annotation type="2">
    <metadata>
      <id>0</id>
      <auteur>Reference</auteur>
      <date>14/10/14 19:22</date>
      <document>Lieu-dit.html</document>
    </metadata>
    <SEval type="axe_intentionnel" idSE="0">
      <descriptive value="1" />
      <narrative value="0" />
      <explicative value="0" />
      <prescriptive value="0" />
      <procedurale value="0" />
      <argumentative value="0" />
      <intentionnel_autre value="0" />
    </SEval>
  </annotation>
  <annotation type="2">
    <metadata>
      <id>0</id>
      <auteur>Reference</auteur>
      <date>14/10/14 19:22</date>
      <document>Lieu-dit.html</document>
    </metadata>
    <SEval type="axe_semantique" idSE="0">
      <visee_ontologique value="0">
        <isA value="0" />
        <partOf value="0" />
        <instanceOf value="0" />
        <ontologique_autre value="0" />
      </visee_ontologique>
      <metalinguistique value="1">
        <hyperonymie value="1" />
        <meronymie value="0" />
        <homonymie value="0" />
        <synonymie value="0" />
        <multilingue value="0" />
        <lexical_autre value="0" />
      </metalinguistique>
      <semantique_autre value="0" />
      <contextuelle value="0" />
    </SEval>
  </annotation>
  <annotation type="2">
    <metadata>
      <id>1</id>
      <auteur>Autre</auteur>
      <date>3/01/14 17:47</date>
      <document>Lieu-dit.html</document>
    </metadata>
    <SEval type="axe_visuel" idSE="1">
      <horizontale value="0" />
      <verticale value="1" />
      <navigationnelle value="0" />
      <hypertextuelle value="0" />
    </SEval>
  </annotation>
  <annotation type="2">
    <metadata>
      <id>1</id>
      <auteur>Autre</auteur>
      <date>3/01/14 17:47</date>
      <document>Lieu-dit.html</document>
    </metadata>
    <SEval type="axe_rhetorique" idSE="1">
      <paradigmatique value="1" />
      <syntagmatique value="0" />
      <hybride value="0" />
      <bivalente value="0" />
    </SEval>
  </annotation>
  <annotation type="2">
    <metadata>
      <id>1</id>
      <auteur>Autre</auteur>
      <date>3/01/14 17:47</date>
      <document>Lieu-dit.html</document>
    </metadata>
    <SEval type="axe_intentionnel" idSE="1">
      <descriptive value="1" />
      <narrative value="0" />
      <explicative value="0" />
      <prescriptive value="0" />
      <procedurale value="0" />
      <argumentative value="0" />
      <intentionnel_autre value="0" />
    </SEval>
  </annotation>
  <annotation type="2">
    <metadata>
      <id>1</id>
      <auteur>Autre</auteur>
      <date>3/01/14 17:47</date>
      <document>Lieu-dit.html</document>
    </metadata>
    <SEval type="axe_semantique" idSE="1">
      <visee_ontologique value="0">
        <isA value="0" />
        <partOf value="0" />
        <instanceOf value="0" />
        <ontologique_autre value="0" />
      </visee_ontologique>
      <metalinguistique value="1">
        <hyperonymie value="1" />
        <meronymie value="0" />
        <homonymie value="0" />
        <synonymie value="0" />
        <multilingue value="0" />
        <lexical_autre value="0" />
      </metalinguistique>
      <semantique_autre value="0" />
      <contextuelle value="0" />
    </SEval>
  </annotation>
  <annotation type="2">
    <metadata>
      <id>2</id>
      <auteur>Autre</auteur>
      <date>3/01/14 17:48</date>
      <document>Lieu-dit.html</document>
    </metadata>
    <SEval type="axe_visuel" idSE="2">
      <horizontale value="0" />
      <verticale value="1" />
      <navigationnelle value="0" />
      <hypertextuelle value="1" />
    </SEval>
  </annotation>
  <annotation type="2">
    <metadata>
      <id>2</id>
      <auteur>Autre</auteur>
      <date>3/01/14 17:48</date>
      <document>Lieu-dit.html</document>
    </metadata>
    <SEval type="axe_rhetorique" idSE="2">
      <paradigmatique value="0" />
      <syntagmatique value="0" />
      <hybride value="0" />
      <bivalente value="0" />
    </SEval>
  </annotation>
  <annotation type="2">
    <metadata>
      <id>2</id>
      <auteur>Autre</auteur>
      <date>3/01/14 17:48</date>
      <document>Lieu-dit.html</document>
    </metadata>
    <SEval type="axe_intentionnel" idSE="2">
      <descriptive value="1" />
      <narrative value="0" />
      <explicative value="0" />
      <prescriptive value="0" />
      <procedurale value="0" />
      <argumentative value="0" />
      <intentionnel_autre value="0" />
    </SEval>
  </annotation>
  <annotation type="2">
    <metadata>
      <id>2</id>
      <auteur>Autre</auteur>
      <date>3/01/14 17:48</date>
      <document>Lieu-dit.html</document>
    </metadata>
    <SEval type="axe_semantique" idSE="2">
      <visee_ontologique value="0">
        <isA value="0" />
        <partOf value="0" />
        <instanceOf value="0" />
        <ontologique_autre value="0" />
      </visee_ontologique>
      <metalinguistique value="1">
        <hyperonymie value="1" />
        <meronymie value="0" />
        <homonymie value="0" />
        <synonymie value="0" />
        <multilingue value="0" />
        <lexical_autre value="0" />
      </metalinguistique>
      <semantique_autre value="0" />
      <contextuelle value="0" />
    </SEval>
  </annotation>
  <annotation type="2">
    <metadata>
      <id>3</id>
      <auteur>Autre</auteur>
      <date>3/01/14 17:49</date>
      <document>Lieu-dit.html</document>
    </metadata>
    <SEval type="axe_visuel" idSE="3">
      <horizontale value="0" />
      <verticale value="1" />
      <navigationnelle value="0" />
      <hypertextuelle value="1" />
    </SEval>
  </annotation>
  <annotation type="2">
    <metadata>
      <id>3</id>
      <auteur>Autre</auteur>
      <date>3/01/14 17:49</date>
      <document>Lieu-dit.html</document>
    </metadata>
    <SEval type="axe_rhetorique" idSE="3">
      <paradigmatique value="1" />
      <syntagmatique value="0" />
      <hybride value="0" />
      <bivalente value="0" />
    </SEval>
  </annotation>
  <annotation type="2">
    <metadata>
      <id>3</id>
      <auteur>Autre</auteur>
      <date>3/01/14 17:49</date>
      <document>Lieu-dit.html</document>
    </metadata>
    <SEval type="axe_intentionnel" idSE="3">
      <descriptive value="1" />
      <narrative value="0" />
      <explicative value="0" />
      <prescriptive value="0" />
      <procedurale value="0" />
      <argumentative value="0" />
      <intentionnel_autre value="0" />
    </SEval>
  </annotation>
  <annotation type="2">
    <metadata>
      <id>3</id>
      <auteur>Autre</auteur>
      <date>3/01/14 17:49</date>
      <document>Lieu-dit.html</document>
    </metadata>
    <SEval type="axe_semantique" idSE="3">
      <visee_ontologique value="0">
        <isA value="0" />
        <partOf value="0" />
        <instanceOf value="0" />
        <ontologique_autre value="0" />
      </visee_ontologique>
      <metalinguistique value="1">
        <hyperonymie value="1" />
        <meronymie value="0" />
        <homonymie value="0" />
        <synonymie value="0" />
        <multilingue value="0" />
        <lexical_autre value="0" />
      </metalinguistique>
      <semantique_autre value="0" />
      <contextuelle value="0" />
    </SEval>
  </annotation>
</root>
