<?xml version="1.0" encoding="UTF-8"?>
<root>
  <annotation type="1">
    <metadata>
      <id>0</id>
      <auteur>Reference</auteur>
      <date>14/10/14 19:22</date>
      <document>Menhir.html</document>
    </metadata>
    <SE>
      <id>0</id>
      <text>Dans les autres régions de France, avant la diffusion du terme « menhir », on utilise des locutions comme « pierre fichée », « pierre plantée », « pierre levée », « pierre longue » ou leur équivalent en langue régionale, lesquels sont souvent présents dans la toponymie sur les cadastres (« Pierrefiche », « Pierrefitte », etc.).</text>
      <span begin="1931" end="2260" />
    </SE>
    <comment>Consensus</comment>
  </annotation>
  <annotation type="1">
    <metadata>
      <id>1</id>
      <auteur>Autre</auteur>
      <date>1/01/13 11:56</date>
      <document>Menhir.html</document>
    </metadata>
    <SE>
      <id>1</id>
      <text>Le matériau employé dépend de la région (granite, porphyre, etc.).</text>
      <span begin="4665" end="4731" />
    </SE>
    <comment />
  </annotation>
  <annotation type="1">
    <metadata>
      <id>2</id>
      <auteur>Autre</auteur>
      <date>1/01/13 11:57</date>
      <document>Menhir.html</document>
    </metadata>
    <SE>
      <id>2</id>
      <text>Leur taille varie fortement, de quelques dizaines de centimètres à plusieurs mètres de hauteur. La pierre peut être taillée (en forme de colonne, d'amande, de dalleanthropomorphe, etc.)</text>
      <span begin="4732" end="4917" />
    </SE>
    <comment>ellipse partielle dans l'amorce (formes de taille)</comment>
  </annotation>
  <annotation type="1">
    <metadata>
      <id>3</id>
      <auteur>Autre</auteur>
      <date>1/01/13 11:58</date>
      <document>Menhir.html</document>
    </metadata>
    <SE>
      <id>3</id>
      <text>Certains menhirs, érigées entre le Néolithique final et l'âge du bronze, sont gravés et taillés de façon anthropomorphe. Ces statues-menhirs sont gravés (parfois sur les deux faces) d'attributs en bas-relief (parfois sculptés en ronde-bosse) comme le visage, les seins, les bras avec les mains, les jambes et les pieds, mais aussi les parures (colliers, pendeloque, crosse, objet mystérieux)</text>
      <span begin="5739" end="6130" />
    </SE>
    <comment />
  </annotation>
  <annotation type="1">
    <metadata>
      <id>4</id>
      <auteur>Autre</auteur>
      <date>1/01/13 12:00</date>
      <document>Menhir.html</document>
    </metadata>
    <SE>
      <id>4</id>
      <text>On les retrouve à travers toute l'Europe, de la zone méridionale (Portugal, Espagne, Corse, etc.)</text>
      <span begin="6826" end="6923" />
    </SE>
    <comment />
  </annotation>
  <annotation type="1">
    <metadata>
      <id>5</id>
      <auteur>Autre</auteur>
      <date>1/01/13 12:01</date>
      <document>Menhir.html</document>
    </metadata>
    <SE>
      <id>5</id>
      <text>On les retrouve à travers toute l'Europe, de la zone méridionale (Portugal, Espagne, Corse, etc.) au pourtour de l'océan Atlantique (France, Irlande, Grande-Bretagne),</text>
      <span begin="6826" end="6994" />
    </SE>
    <comment />
  </annotation>
  <annotation type="1">
    <metadata>
      <id>6</id>
      <auteur>Autre</auteur>
      <date>1/01/13 12:02</date>
      <document>Menhir.html</document>
    </metadata>
    <SE>
      <id>6</id>
      <text>On les retrouve à travers toute l'Europe, de la zone méridionale (Portugal, Espagne, Corse, etc.) au pourtour de l'océan Atlantique (France, Irlande, Grande-Bretagne), et de l'Europe centrale (Suisse, Autriche, Allemagne)</text>
      <span begin="6826" end="7048" />
    </SE>
    <comment />
  </annotation>
  <annotation type="1">
    <metadata>
      <id>7</id>
      <auteur>Autre</auteur>
      <date>8/01/13 13:04</date>
      <document>Menhir.html</document>
    </metadata>
    <SE>
      <id>7</id>
      <text>On les retrouve à travers toute l'Europe, de la zone méridionale (Portugal, Espagne, Corse, etc.) au pourtour de l'océan Atlantique (France, Irlande, Grande-Bretagne), et de l'Europe centrale (Suisse, Autriche, Allemagne) à la Scandinavie (Danemark et Suède).</text>
      <span begin="6826" end="7085" />
    </SE>
    <comment />
  </annotation>
  <annotation type="1">
    <metadata>
      <id>8</id>
      <auteur>Autre</auteur>
      <date>1/01/13 12:03</date>
      <document>Menhir.html</document>
    </metadata>
    <SE>
      <id>8</id>
      <text>Sous des formes plus récentes, les menhirs se rencontrent également en Afrique (Sénégal), en Asie (Inde, Indonésie, Corée)</text>
      <span begin="7369" end="7491" />
    </SE>
    <comment />
  </annotation>
  <annotation type="2">
    <metadata>
      <id>0</id>
      <auteur>Reference</auteur>
      <date>14/10/14 19:22</date>
      <document>Menhir.html</document>
    </metadata>
    <SEval type="primer_syntax" idSE="0" />
  </annotation>
  <annotation type="2">
    <metadata>
      <id>0</id>
      <auteur>Reference</auteur>
      <date>14/10/14 19:22</date>
      <document>Menhir.html</document>
    </metadata>
    <SEval type="items_syntax" idSE="0">
      <item id="0" />
      <item id="1" />
      <item id="2" />
    </SEval>
  </annotation>
  <annotation type="2">
    <metadata>
      <id>1</id>
      <auteur>Autre</auteur>
      <date>1/01/13 11:56</date>
      <document>Menhir.html</document>
    </metadata>
    <SEval type="primer_syntax" idSE="1" />
  </annotation>
  <annotation type="2">
    <metadata>
      <id>1</id>
      <auteur>Autre</auteur>
      <date>1/01/13 11:56</date>
      <document>Menhir.html</document>
    </metadata>
    <SEval type="items_syntax" idSE="1">
      <item id="0" />
      <item id="1" />
      <item id="2" />
    </SEval>
  </annotation>
  <annotation type="2">
    <metadata>
      <id>2</id>
      <auteur>Autre</auteur>
      <date>1/01/13 11:57</date>
      <document>Menhir.html</document>
    </metadata>
    <SEval type="primer_syntax" idSE="2" />
  </annotation>
  <annotation type="2">
    <metadata>
      <id>2</id>
      <auteur>Autre</auteur>
      <date>1/01/13 11:57</date>
      <document>Menhir.html</document>
    </metadata>
    <SEval type="items_syntax" idSE="2">
      <item id="0" />
      <item id="1" />
      <item id="2" />
      <item id="3" />
    </SEval>
  </annotation>
  <annotation type="2">
    <metadata>
      <id>3</id>
      <auteur>Autre</auteur>
      <date>1/01/13 11:58</date>
      <document>Menhir.html</document>
    </metadata>
    <SEval type="primer_syntax" idSE="3" />
  </annotation>
  <annotation type="2">
    <metadata>
      <id>3</id>
      <auteur>Autre</auteur>
      <date>1/01/13 11:58</date>
      <document>Menhir.html</document>
    </metadata>
    <SEval type="items_syntax" idSE="3">
      <item id="0" />
      <item id="1" />
      <item id="2" />
      <item id="3" />
    </SEval>
  </annotation>
  <annotation type="2">
    <metadata>
      <id>4</id>
      <auteur>Autre</auteur>
      <date>1/01/13 12:00</date>
      <document>Menhir.html</document>
    </metadata>
    <SEval type="primer_syntax" idSE="4" />
  </annotation>
  <annotation type="2">
    <metadata>
      <id>4</id>
      <auteur>Autre</auteur>
      <date>1/01/13 12:00</date>
      <document>Menhir.html</document>
    </metadata>
    <SEval type="items_syntax" idSE="4">
      <item id="0" />
      <item id="1" />
      <item id="2" />
      <item id="3" />
    </SEval>
  </annotation>
  <annotation type="2">
    <metadata>
      <id>5</id>
      <auteur>Autre</auteur>
      <date>1/01/13 12:01</date>
      <document>Menhir.html</document>
    </metadata>
    <SEval type="primer_syntax" idSE="5" />
  </annotation>
  <annotation type="2">
    <metadata>
      <id>5</id>
      <auteur>Autre</auteur>
      <date>1/01/13 12:01</date>
      <document>Menhir.html</document>
    </metadata>
    <SEval type="items_syntax" idSE="5">
      <item id="0" />
      <item id="1" />
      <item id="2" />
    </SEval>
  </annotation>
  <annotation type="2">
    <metadata>
      <id>6</id>
      <auteur>Autre</auteur>
      <date>1/01/13 12:02</date>
      <document>Menhir.html</document>
    </metadata>
    <SEval type="primer_syntax" idSE="6" />
  </annotation>
  <annotation type="2">
    <metadata>
      <id>6</id>
      <auteur>Autre</auteur>
      <date>1/01/13 12:02</date>
      <document>Menhir.html</document>
    </metadata>
    <SEval type="items_syntax" idSE="6">
      <item id="0" />
      <item id="1" />
      <item id="2" />
    </SEval>
  </annotation>
  <annotation type="2">
    <metadata>
      <id>7</id>
      <auteur>Autre</auteur>
      <date>8/01/13 13:04</date>
      <document>Menhir.html</document>
    </metadata>
    <SEval type="primer_syntax" idSE="7" />
  </annotation>
  <annotation type="2">
    <metadata>
      <id>7</id>
      <auteur>Autre</auteur>
      <date>8/01/13 13:04</date>
      <document>Menhir.html</document>
    </metadata>
    <SEval type="items_syntax" idSE="7">
      <item id="0" />
      <item id="1" />
    </SEval>
  </annotation>
  <annotation type="2">
    <metadata>
      <id>8</id>
      <auteur>Autre</auteur>
      <date>1/01/13 12:03</date>
      <document>Menhir.html</document>
    </metadata>
    <SEval type="primer_syntax" idSE="8" />
  </annotation>
  <annotation type="2">
    <metadata>
      <id>8</id>
      <auteur>Autre</auteur>
      <date>1/01/13 12:03</date>
      <document>Menhir.html</document>
    </metadata>
    <SEval type="items_syntax" idSE="8">
      <item id="0" />
      <item id="1" />
      <item id="2" />
    </SEval>
  </annotation>
  <annotation type="2">
    <metadata>
      <id>0</id>
      <auteur>Reference</auteur>
      <date>14/10/14 19:22</date>
      <document>Menhir.html</document>
    </metadata>
    <SEval type="primer" idSE="0">
      <span begin="1" end="290" />
      <text>Dans les autres régions de France, avant la diffusion du terme « menhir », on utilise des locutions comme « pierre fichée », « pierre plantée », « pierre levée », « pierre longue » ou leur équivalent en langue régionale, lesquels sont souvent présents dans la toponymie sur les cadastres (</text>
    </SEval>
  </annotation>
  <annotation type="2">
    <metadata>
      <id>0</id>
      <auteur>Reference</auteur>
      <date>14/10/14 19:22</date>
      <document>Menhir.html</document>
    </metadata>
    <SEval type="items" idSE="0">
      <span begin="289" end="306" id="0" />
      <text id="0">(« Pierrefiche »,</text>
      <span begin="307" end="323" id="1" />
      <text id="1">« Pierrefitte »,</text>
      <span begin="324" end="330" id="2" />
      <text id="2">etc.).</text>
    </SEval>
  </annotation>
  <annotation type="2">
    <metadata>
      <id>1</id>
      <auteur>Autre</auteur>
      <date>1/01/13 11:56</date>
      <document>Menhir.html</document>
    </metadata>
    <SEval type="primer" idSE="1">
      <span begin="1" end="42" />
      <text>Le matériau employé dépend de la région (</text>
    </SEval>
  </annotation>
  <annotation type="2">
    <metadata>
      <id>1</id>
      <auteur>Autre</auteur>
      <date>1/01/13 11:56</date>
      <document>Menhir.html</document>
    </metadata>
    <SEval type="items" idSE="1">
      <span begin="42" end="51" id="0" />
      <text id="0">granite,</text>
      <span begin="50" end="60" id="1" />
      <text id="1">porphyre,</text>
      <span begin="60" end="67" id="2" />
      <text id="2">etc.).</text>
    </SEval>
  </annotation>
  <annotation type="2">
    <metadata>
      <id>2</id>
      <auteur>Autre</auteur>
      <date>1/01/13 11:57</date>
      <document>Menhir.html</document>
    </metadata>
    <SEval type="primer" idSE="2">
      <span begin="1" end="126" />
      <text>Leur taille varie fortement, de quelques dizaines de centimètres à plusieurs mètres de hauteur. La pierre peut être taillée (</text>
    </SEval>
  </annotation>
  <annotation type="2">
    <metadata>
      <id>2</id>
      <auteur>Autre</auteur>
      <date>1/01/13 11:57</date>
      <document>Menhir.html</document>
    </metadata>
    <SEval type="items" idSE="2">
      <span begin="126" end="147" id="0" />
      <text id="0">en forme de colonne,</text>
      <span begin="147" end="156" id="1" />
      <text id="1">d'amande,</text>
      <span begin="157" end="180" id="2" />
      <text id="2">de dalleanthropomorphe,</text>
      <span begin="181" end="186" id="3" />
      <text id="3">etc.)</text>
    </SEval>
  </annotation>
  <annotation type="2">
    <metadata>
      <id>3</id>
      <auteur>Autre</auteur>
      <date>1/01/13 11:58</date>
      <document>Menhir.html</document>
    </metadata>
    <SEval type="primer" idSE="3">
      <span begin="1" end="345" />
      <text>Certains menhirs, érigées entre le Néolithique final et l'âge du bronze, sont gravés et taillés de façon anthropomorphe. Ces statues-menhirs sont gravés (parfois sur les deux faces) d'attributs en bas-relief (parfois sculptés en ronde-bosse) comme le visage, les seins, les bras avec les mains, les jambes et les pieds, mais aussi les parures (</text>
    </SEval>
  </annotation>
  <annotation type="2">
    <metadata>
      <id>3</id>
      <auteur>Autre</auteur>
      <date>1/01/13 11:58</date>
      <document>Menhir.html</document>
    </metadata>
    <SEval type="items" idSE="3">
      <span begin="344" end="354" id="0" />
      <text id="0">(colliers,</text>
      <span begin="355" end="366" id="1" />
      <text id="1">pendeloque,</text>
      <span begin="367" end="374" id="2" />
      <text id="2">crosse,</text>
      <span begin="375" end="392" id="3" />
      <text id="3">objet mystérieux)</text>
    </SEval>
  </annotation>
  <annotation type="2">
    <metadata>
      <id>4</id>
      <auteur>Autre</auteur>
      <date>1/01/13 12:00</date>
      <document>Menhir.html</document>
    </metadata>
    <SEval type="primer" idSE="4">
      <span begin="1" end="67" />
      <text>On les retrouve à travers toute l'Europe, de la zone méridionale (</text>
    </SEval>
  </annotation>
  <annotation type="2">
    <metadata>
      <id>4</id>
      <auteur>Autre</auteur>
      <date>1/01/13 12:00</date>
      <document>Menhir.html</document>
    </metadata>
    <SEval type="items" idSE="4">
      <span begin="67" end="76" id="0" />
      <text id="0">Portugal,</text>
      <span begin="76" end="86" id="1" />
      <text id="1">Espagne,</text>
      <span begin="84" end="92" id="2" />
      <text id="2">, Corse,</text>
      <span begin="92" end="98" id="3" />
      <text id="3">etc.)</text>
    </SEval>
  </annotation>
  <annotation type="2">
    <metadata>
      <id>5</id>
      <auteur>Autre</auteur>
      <date>1/01/13 12:01</date>
      <document>Menhir.html</document>
    </metadata>
    <SEval type="primer" idSE="5">
      <span begin="1" end="134" />
      <text>On les retrouve à travers toute l'Europe, de la zone méridionale (Portugal, Espagne, Corse, etc.) au pourtour de l'océan Atlantique (</text>
    </SEval>
  </annotation>
  <annotation type="2">
    <metadata>
      <id>5</id>
      <auteur>Autre</auteur>
      <date>1/01/13 12:01</date>
      <document>Menhir.html</document>
    </metadata>
    <SEval type="items" idSE="5">
      <span begin="131" end="141" id="0" />
      <text id="0">e (France,</text>
      <span begin="141" end="150" id="1" />
      <text id="1">Irlande,</text>
      <span begin="151" end="168" id="2" />
      <text id="2">Grande-Bretagne),</text>
    </SEval>
  </annotation>
  <annotation type="2">
    <metadata>
      <id>6</id>
      <auteur>Autre</auteur>
      <date>1/01/13 12:02</date>
      <document>Menhir.html</document>
    </metadata>
    <SEval type="primer" idSE="6">
      <span begin="1" end="194" />
      <text>On les retrouve à travers toute l'Europe, de la zone méridionale (Portugal, Espagne, Corse, etc.) au pourtour de l'océan Atlantique (France, Irlande, Grande-Bretagne), et de l'Europe centrale (</text>
    </SEval>
  </annotation>
  <annotation type="2">
    <metadata>
      <id>6</id>
      <auteur>Autre</auteur>
      <date>1/01/13 12:02</date>
      <document>Menhir.html</document>
    </metadata>
    <SEval type="items" idSE="6">
      <span begin="193" end="201" id="0" />
      <text id="0">(Suisse,</text>
      <span begin="202" end="211" id="1" />
      <text id="1">Autriche,</text>
      <span begin="212" end="222" id="2" />
      <text id="2">Allemagne)</text>
    </SEval>
  </annotation>
  <annotation type="2">
    <metadata>
      <id>7</id>
      <auteur>Autre</auteur>
      <date>8/01/13 13:04</date>
      <document>Menhir.html</document>
    </metadata>
    <SEval type="primer" idSE="7">
      <span begin="1" end="241" />
      <text>On les retrouve à travers toute l'Europe, de la zone méridionale (Portugal, Espagne, Corse, etc.) au pourtour de l'océan Atlantique (France, Irlande, Grande-Bretagne), et de l'Europe centrale (Suisse, Autriche, Allemagne) à la Scandinavie (</text>
    </SEval>
  </annotation>
  <annotation type="2">
    <metadata>
      <id>7</id>
      <auteur>Autre</auteur>
      <date>8/01/13 13:04</date>
      <document>Menhir.html</document>
    </metadata>
    <SEval type="items" idSE="7">
      <span begin="236" end="252" id="0" />
      <text id="0">vie (Danemark et</text>
      <span begin="253" end="260" id="1" />
      <text id="1">Suède).</text>
    </SEval>
  </annotation>
  <annotation type="2">
    <metadata>
      <id>8</id>
      <auteur>Autre</auteur>
      <date>1/01/13 12:03</date>
      <document>Menhir.html</document>
    </metadata>
    <SEval type="primer" idSE="8">
      <span begin="1" end="100" />
      <text>Sous des formes plus récentes, les menhirs se rencontrent également en Afrique (Sénégal), en Asie (</text>
    </SEval>
  </annotation>
  <annotation type="2">
    <metadata>
      <id>8</id>
      <auteur>Autre</auteur>
      <date>1/01/13 12:03</date>
      <document>Menhir.html</document>
    </metadata>
    <SEval type="items" idSE="8">
      <span begin="97" end="105" id="0" />
      <text id="0">e (Inde,</text>
      <span begin="105" end="116" id="1" />
      <text id="1">Indonésie,</text>
      <span begin="117" end="123" id="2" />
      <text id="2">Corée)</text>
    </SEval>
  </annotation>
  <annotation type="2">
    <metadata>
      <id>0</id>
      <auteur>Reference</auteur>
      <date>14/10/14 19:22</date>
      <document>Menhir.html</document>
    </metadata>
    <SEval type="concept" idSE="0" localisation="primer" idItem="-1">
      <span begin="66" end="73" id="0" />
      <text id="0">menhir</text>
    </SEval>
  </annotation>
  <annotation type="2">
    <metadata>
      <id>0</id>
      <auteur>Reference</auteur>
      <date>14/10/14 19:22</date>
      <document>Menhir.html</document>
    </metadata>
    <SEval type="concept" idSE="0" localisation="item" idItem="0">
      <span begin="292" end="303" id="0" />
      <text id="0">Pierrefiche</text>
    </SEval>
  </annotation>
  <annotation type="2">
    <metadata>
      <id>0</id>
      <auteur>Reference</auteur>
      <date>14/10/14 19:22</date>
      <document>Menhir.html</document>
    </metadata>
    <SEval type="concept" idSE="0" localisation="item" idItem="1">
      <span begin="309" end="320" id="0" />
      <text id="0">Pierrefitte</text>
    </SEval>
  </annotation>
  <annotation type="2">
    <metadata>
      <id>1</id>
      <auteur>Autre</auteur>
      <date>1/01/13 11:56</date>
      <document>Menhir.html</document>
    </metadata>
    <SEval type="concept" idSE="1" localisation="primer" idItem="-1">
      <span begin="1" end="12" id="0" />
      <text id="0">Le matériau</text>
    </SEval>
  </annotation>
  <annotation type="2">
    <metadata>
      <id>1</id>
      <auteur>Autre</auteur>
      <date>1/01/13 11:56</date>
      <document>Menhir.html</document>
    </metadata>
    <SEval type="concept" idSE="1" localisation="item" idItem="0">
      <span begin="42" end="49" id="0" />
      <text id="0">granite</text>
    </SEval>
  </annotation>
  <annotation type="2">
    <metadata>
      <id>1</id>
      <auteur>Autre</auteur>
      <date>1/01/13 11:56</date>
      <document>Menhir.html</document>
    </metadata>
    <SEval type="concept" idSE="1" localisation="item" idItem="1">
      <span begin="51" end="59" id="0" />
      <text id="0">porphyre</text>
    </SEval>
  </annotation>
  <annotation type="2">
    <metadata>
      <id>2</id>
      <auteur>Autre</auteur>
      <date>1/01/13 11:57</date>
      <document>Menhir.html</document>
    </metadata>
    <SEval type="concept" idSE="2" localisation="item" idItem="0">
      <span begin="138" end="145" id="0" />
      <text id="0">colonne</text>
    </SEval>
  </annotation>
  <annotation type="2">
    <metadata>
      <id>2</id>
      <auteur>Autre</auteur>
      <date>1/01/13 11:57</date>
      <document>Menhir.html</document>
    </metadata>
    <SEval type="concept" idSE="2" localisation="item" idItem="1">
      <span begin="149" end="155" id="0" />
      <text id="0">amande</text>
    </SEval>
  </annotation>
  <annotation type="2">
    <metadata>
      <id>2</id>
      <auteur>Autre</auteur>
      <date>1/01/13 11:57</date>
      <document>Menhir.html</document>
    </metadata>
    <SEval type="concept" idSE="2" localisation="item" idItem="2">
      <span begin="159" end="179" id="0" />
      <text id="0">dalleanthropomorphe</text>
    </SEval>
  </annotation>
  <annotation type="2">
    <metadata>
      <id>2</id>
      <auteur>Autre</auteur>
      <date>1/01/13 11:57</date>
      <document>Menhir.html</document>
    </metadata>
    <SEval type="marq_relation" idSE="2" localisation="item" idItem="0">
      <span begin="126" end="137" id="0" />
      <text id="0">en forme de</text>
    </SEval>
  </annotation>
  <annotation type="2">
    <metadata>
      <id>3</id>
      <auteur>Autre</auteur>
      <date>1/01/13 11:58</date>
      <document>Menhir.html</document>
    </metadata>
    <SEval type="concept" idSE="3" localisation="primer" idItem="-1">
      <span begin="332" end="343" id="0" />
      <text id="0">les parures</text>
    </SEval>
  </annotation>
  <annotation type="2">
    <metadata>
      <id>3</id>
      <auteur>Autre</auteur>
      <date>1/01/13 11:58</date>
      <document>Menhir.html</document>
    </metadata>
    <SEval type="concept" idSE="3" localisation="item" idItem="0">
      <span begin="345" end="353" id="0" />
      <text id="0">colliers</text>
    </SEval>
  </annotation>
  <annotation type="2">
    <metadata>
      <id>3</id>
      <auteur>Autre</auteur>
      <date>1/01/13 11:58</date>
      <document>Menhir.html</document>
    </metadata>
    <SEval type="concept" idSE="3" localisation="item" idItem="1">
      <span begin="355" end="365" id="0" />
      <text id="0">pendeloque</text>
    </SEval>
  </annotation>
  <annotation type="2">
    <metadata>
      <id>3</id>
      <auteur>Autre</auteur>
      <date>1/01/13 11:58</date>
      <document>Menhir.html</document>
    </metadata>
    <SEval type="concept" idSE="3" localisation="item" idItem="2">
      <span begin="367" end="373" id="0" />
      <text id="0">crosse</text>
    </SEval>
  </annotation>
  <annotation type="2">
    <metadata>
      <id>3</id>
      <auteur>Autre</auteur>
      <date>1/01/13 11:58</date>
      <document>Menhir.html</document>
    </metadata>
    <SEval type="concept" idSE="3" localisation="item" idItem="3">
      <span begin="375" end="391" id="0" />
      <text id="0">objet mystérieux</text>
    </SEval>
  </annotation>
  <annotation type="2">
    <metadata>
      <id>4</id>
      <auteur>Autre</auteur>
      <date>1/01/13 12:00</date>
      <document>Menhir.html</document>
    </metadata>
    <SEval type="concept" idSE="4" localisation="primer" idItem="-1">
      <span begin="48" end="65" id="0" />
      <text id="0">zone méridionale</text>
    </SEval>
  </annotation>
  <annotation type="2">
    <metadata>
      <id>4</id>
      <auteur>Autre</auteur>
      <date>1/01/13 12:00</date>
      <document>Menhir.html</document>
    </metadata>
    <SEval type="concept" idSE="4" localisation="item" idItem="0">
      <span begin="67" end="76" id="0" />
      <text id="0">Portugal,</text>
    </SEval>
  </annotation>
  <annotation type="2">
    <metadata>
      <id>4</id>
      <auteur>Autre</auteur>
      <date>1/01/13 12:00</date>
      <document>Menhir.html</document>
    </metadata>
    <SEval type="concept" idSE="4" localisation="item" idItem="1">
      <span begin="76" end="84" id="0" />
      <text id="0">Espagne</text>
    </SEval>
  </annotation>
  <annotation type="2">
    <metadata>
      <id>4</id>
      <auteur>Autre</auteur>
      <date>1/01/13 12:00</date>
      <document>Menhir.html</document>
    </metadata>
    <SEval type="concept" idSE="4" localisation="item" idItem="2">
      <span begin="86" end="91" id="0" />
      <text id="0">Corse</text>
    </SEval>
  </annotation>
  <annotation type="2">
    <metadata>
      <id>4</id>
      <auteur>Autre</auteur>
      <date>1/01/13 12:00</date>
      <document>Menhir.html</document>
    </metadata>
    <SEval type="circonstant" idSE="4" localisation="primer" idItem="-1">
      <span begin="35" end="41" id="0" />
      <text id="0">Europe</text>
    </SEval>
  </annotation>
  <annotation type="2">
    <metadata>
      <id>5</id>
      <auteur>Autre</auteur>
      <date>1/01/13 12:01</date>
      <document>Menhir.html</document>
    </metadata>
    <SEval type="concept" idSE="5" localisation="primer" idItem="-1">
      <span begin="101" end="133" id="0" />
      <text id="0">pourtour de l'océan Atlantique</text>
    </SEval>
  </annotation>
  <annotation type="2">
    <metadata>
      <id>5</id>
      <auteur>Autre</auteur>
      <date>1/01/13 12:01</date>
      <document>Menhir.html</document>
    </metadata>
    <SEval type="concept" idSE="5" localisation="item" idItem="0">
      <span begin="134" end="140" id="0" />
      <text id="0">France</text>
    </SEval>
  </annotation>
  <annotation type="2">
    <metadata>
      <id>5</id>
      <auteur>Autre</auteur>
      <date>1/01/13 12:01</date>
      <document>Menhir.html</document>
    </metadata>
    <SEval type="concept" idSE="5" localisation="item" idItem="1">
      <span begin="142" end="149" id="0" />
      <text id="0">Irlande</text>
    </SEval>
  </annotation>
  <annotation type="2">
    <metadata>
      <id>5</id>
      <auteur>Autre</auteur>
      <date>1/01/13 12:01</date>
      <document>Menhir.html</document>
    </metadata>
    <SEval type="concept" idSE="5" localisation="item" idItem="2">
      <span begin="151" end="166" id="0" />
      <text id="0">Grande-Bretagne</text>
    </SEval>
  </annotation>
  <annotation type="2">
    <metadata>
      <id>5</id>
      <auteur>Autre</auteur>
      <date>1/01/13 12:01</date>
      <document>Menhir.html</document>
    </metadata>
    <SEval type="circonstant" idSE="5" localisation="primer" idItem="-1">
      <span begin="35" end="41" id="0" />
      <text id="0">Europe</text>
    </SEval>
  </annotation>
  <annotation type="2">
    <metadata>
      <id>6</id>
      <auteur>Autre</auteur>
      <date>1/01/13 12:02</date>
      <document>Menhir.html</document>
    </metadata>
    <SEval type="concept" idSE="6" localisation="primer" idItem="-1">
      <span begin="176" end="192" id="0" />
      <text id="0">'Europe centrale</text>
    </SEval>
  </annotation>
  <annotation type="2">
    <metadata>
      <id>6</id>
      <auteur>Autre</auteur>
      <date>1/01/13 12:02</date>
      <document>Menhir.html</document>
    </metadata>
    <SEval type="concept" idSE="6" localisation="item" idItem="0">
      <span begin="194" end="200" id="0" />
      <text id="0">Suisse</text>
    </SEval>
  </annotation>
  <annotation type="2">
    <metadata>
      <id>6</id>
      <auteur>Autre</auteur>
      <date>1/01/13 12:02</date>
      <document>Menhir.html</document>
    </metadata>
    <SEval type="concept" idSE="6" localisation="item" idItem="1">
      <span begin="202" end="210" id="0" />
      <text id="0">Autriche</text>
    </SEval>
  </annotation>
  <annotation type="2">
    <metadata>
      <id>6</id>
      <auteur>Autre</auteur>
      <date>1/01/13 12:02</date>
      <document>Menhir.html</document>
    </metadata>
    <SEval type="concept" idSE="6" localisation="item" idItem="2">
      <span begin="212" end="221" id="0" />
      <text id="0">Allemagne</text>
    </SEval>
  </annotation>
  <annotation type="2">
    <metadata>
      <id>6</id>
      <auteur>Autre</auteur>
      <date>1/01/13 12:02</date>
      <document>Menhir.html</document>
    </metadata>
    <SEval type="circonstant" idSE="6" localisation="primer" idItem="-1">
      <span begin="35" end="41" id="0" />
      <text id="0">Europe</text>
    </SEval>
  </annotation>
  <annotation type="2">
    <metadata>
      <id>7</id>
      <auteur>Autre</auteur>
      <date>8/01/13 13:04</date>
      <document>Menhir.html</document>
    </metadata>
    <SEval type="concept" idSE="7" localisation="primer" idItem="-1">
      <span begin="228" end="239" id="0" />
      <text id="0">Scandinavie</text>
    </SEval>
  </annotation>
  <annotation type="2">
    <metadata>
      <id>7</id>
      <auteur>Autre</auteur>
      <date>8/01/13 13:04</date>
      <document>Menhir.html</document>
    </metadata>
    <SEval type="concept" idSE="7" localisation="item" idItem="0">
      <span begin="241" end="249" id="0" />
      <text id="0">Danemark</text>
    </SEval>
  </annotation>
  <annotation type="2">
    <metadata>
      <id>7</id>
      <auteur>Autre</auteur>
      <date>8/01/13 13:04</date>
      <document>Menhir.html</document>
    </metadata>
    <SEval type="concept" idSE="7" localisation="item" idItem="1">
      <span begin="253" end="258" id="0" />
      <text id="0">Suède</text>
    </SEval>
  </annotation>
  <annotation type="2">
    <metadata>
      <id>7</id>
      <auteur>Autre</auteur>
      <date>8/01/13 13:04</date>
      <document>Menhir.html</document>
    </metadata>
    <SEval type="circonstant" idSE="7" localisation="primer" idItem="-1">
      <span begin="35" end="41" id="0" />
      <text id="0">Europe</text>
    </SEval>
  </annotation>
  <annotation type="2">
    <metadata>
      <id>8</id>
      <auteur>Autre</auteur>
      <date>1/01/13 12:03</date>
      <document>Menhir.html</document>
    </metadata>
    <SEval type="concept" idSE="8" localisation="primer" idItem="-1">
      <span begin="94" end="98" id="0" />
      <text id="0">Asie</text>
    </SEval>
  </annotation>
  <annotation type="2">
    <metadata>
      <id>8</id>
      <auteur>Autre</auteur>
      <date>1/01/13 12:03</date>
      <document>Menhir.html</document>
    </metadata>
    <SEval type="concept" idSE="8" localisation="item" idItem="0">
      <span begin="100" end="104" id="0" />
      <text id="0">Inde</text>
    </SEval>
  </annotation>
  <annotation type="2">
    <metadata>
      <id>8</id>
      <auteur>Autre</auteur>
      <date>1/01/13 12:03</date>
      <document>Menhir.html</document>
    </metadata>
    <SEval type="concept" idSE="8" localisation="item" idItem="1">
      <span begin="106" end="115" id="0" />
      <text id="0">Indonésie</text>
    </SEval>
  </annotation>
  <annotation type="2">
    <metadata>
      <id>8</id>
      <auteur>Autre</auteur>
      <date>1/01/13 12:03</date>
      <document>Menhir.html</document>
    </metadata>
    <SEval type="concept" idSE="8" localisation="item" idItem="2">
      <span begin="117" end="122" id="0" />
      <text id="0">Corée</text>
    </SEval>
  </annotation>
  <annotation type="2">
    <metadata>
      <id>0</id>
      <auteur>Reference</auteur>
      <date>14/10/14 19:22</date>
      <document>Menhir.html</document>
    </metadata>
    <SEval type="axe_visuel" idSE="0">
      <horizontale value="1" />
      <verticale value="0" />
      <navigationnelle value="0" />
      <hypertextuelle value="0" />
    </SEval>
  </annotation>
  <annotation type="2">
    <metadata>
      <id>0</id>
      <auteur>Reference</auteur>
      <date>14/10/14 19:22</date>
      <document>Menhir.html</document>
    </metadata>
    <SEval type="axe_rhetorique" idSE="0">
      <paradigmatique value="1" />
      <syntagmatique value="0" />
      <hybride value="0" />
      <bivalente value="0" />
    </SEval>
  </annotation>
  <annotation type="2">
    <metadata>
      <id>0</id>
      <auteur>Reference</auteur>
      <date>14/10/14 19:22</date>
      <document>Menhir.html</document>
    </metadata>
    <SEval type="axe_intentionnel" idSE="0">
      <descriptive value="1" />
      <narrative value="0" />
      <explicative value="0" />
      <prescriptive value="0" />
      <procedurale value="0" />
      <argumentative value="0" />
      <intentionnel_autre value="0" />
    </SEval>
  </annotation>
  <annotation type="2">
    <metadata>
      <id>0</id>
      <auteur>Reference</auteur>
      <date>14/10/14 19:22</date>
      <document>Menhir.html</document>
    </metadata>
    <SEval type="axe_semantique" idSE="0">
      <visee_ontologique value="0">
        <isA value="0" />
        <partOf value="0" />
        <instanceOf value="0" />
        <ontologique_autre value="0" />
      </visee_ontologique>
      <metalinguistique value="1">
        <hyperonymie value="0" />
        <meronymie value="0" />
        <homonymie value="0" />
        <synonymie value="0" />
        <multilingue value="1" />
        <lexical_autre value="0" />
      </metalinguistique>
      <semantique_autre value="0" />
      <contextuelle value="0" />
    </SEval>
  </annotation>
  <annotation type="2">
    <metadata>
      <id>1</id>
      <auteur>Autre</auteur>
      <date>1/01/13 11:56</date>
      <document>Menhir.html</document>
    </metadata>
    <SEval type="axe_visuel" idSE="1">
      <horizontale value="1" />
      <verticale value="0" />
      <navigationnelle value="0" />
      <hypertextuelle value="1" />
    </SEval>
  </annotation>
  <annotation type="2">
    <metadata>
      <id>1</id>
      <auteur>Autre</auteur>
      <date>1/01/13 11:56</date>
      <document>Menhir.html</document>
    </metadata>
    <SEval type="axe_rhetorique" idSE="1">
      <paradigmatique value="1" />
      <syntagmatique value="0" />
      <hybride value="0" />
      <bivalente value="0" />
    </SEval>
  </annotation>
  <annotation type="2">
    <metadata>
      <id>1</id>
      <auteur>Autre</auteur>
      <date>1/01/13 11:56</date>
      <document>Menhir.html</document>
    </metadata>
    <SEval type="axe_intentionnel" idSE="1">
      <descriptive value="1" />
      <narrative value="0" />
      <explicative value="0" />
      <prescriptive value="0" />
      <procedurale value="0" />
      <argumentative value="0" />
      <intentionnel_autre value="0" />
    </SEval>
  </annotation>
  <annotation type="2">
    <metadata>
      <id>1</id>
      <auteur>Autre</auteur>
      <date>1/01/13 11:56</date>
      <document>Menhir.html</document>
    </metadata>
    <SEval type="axe_semantique" idSE="1">
      <visee_ontologique value="1">
        <isA value="1" />
        <partOf value="0" />
        <instanceOf value="0" />
        <ontologique_autre value="0" />
      </visee_ontologique>
      <metalinguistique value="0">
        <hyperonymie value="0" />
        <meronymie value="0" />
        <homonymie value="0" />
        <synonymie value="0" />
        <multilingue value="0" />
        <lexical_autre value="0" />
      </metalinguistique>
      <semantique_autre value="0" />
      <contextuelle value="0" />
    </SEval>
  </annotation>
  <annotation type="2">
    <metadata>
      <id>2</id>
      <auteur>Autre</auteur>
      <date>1/01/13 11:57</date>
      <document>Menhir.html</document>
    </metadata>
    <SEval type="axe_visuel" idSE="2">
      <horizontale value="1" />
      <verticale value="0" />
      <navigationnelle value="0" />
      <hypertextuelle value="1" />
    </SEval>
  </annotation>
  <annotation type="2">
    <metadata>
      <id>2</id>
      <auteur>Autre</auteur>
      <date>1/01/13 11:57</date>
      <document>Menhir.html</document>
    </metadata>
    <SEval type="axe_rhetorique" idSE="2">
      <paradigmatique value="1" />
      <syntagmatique value="0" />
      <hybride value="0" />
      <bivalente value="0" />
    </SEval>
  </annotation>
  <annotation type="2">
    <metadata>
      <id>2</id>
      <auteur>Autre</auteur>
      <date>1/01/13 11:57</date>
      <document>Menhir.html</document>
    </metadata>
    <SEval type="axe_intentionnel" idSE="2">
      <descriptive value="1" />
      <narrative value="0" />
      <explicative value="0" />
      <prescriptive value="0" />
      <procedurale value="0" />
      <argumentative value="0" />
      <intentionnel_autre value="0" />
    </SEval>
  </annotation>
  <annotation type="2">
    <metadata>
      <id>2</id>
      <auteur>Autre</auteur>
      <date>1/01/13 11:57</date>
      <document>Menhir.html</document>
    </metadata>
    <SEval type="axe_semantique" idSE="2">
      <visee_ontologique value="1">
        <isA value="1" />
        <partOf value="0" />
        <instanceOf value="0" />
        <ontologique_autre value="0" />
      </visee_ontologique>
      <metalinguistique value="0">
        <hyperonymie value="0" />
        <meronymie value="0" />
        <homonymie value="0" />
        <synonymie value="0" />
        <multilingue value="0" />
        <lexical_autre value="0" />
      </metalinguistique>
      <semantique_autre value="0" />
      <contextuelle value="0" />
    </SEval>
  </annotation>
  <annotation type="2">
    <metadata>
      <id>3</id>
      <auteur>Autre</auteur>
      <date>1/01/13 11:58</date>
      <document>Menhir.html</document>
    </metadata>
    <SEval type="axe_visuel" idSE="3">
      <horizontale value="1" />
      <verticale value="0" />
      <navigationnelle value="0" />
      <hypertextuelle value="1" />
    </SEval>
  </annotation>
  <annotation type="2">
    <metadata>
      <id>3</id>
      <auteur>Autre</auteur>
      <date>1/01/13 11:58</date>
      <document>Menhir.html</document>
    </metadata>
    <SEval type="axe_rhetorique" idSE="3">
      <paradigmatique value="1" />
      <syntagmatique value="0" />
      <hybride value="0" />
      <bivalente value="0" />
    </SEval>
  </annotation>
  <annotation type="2">
    <metadata>
      <id>3</id>
      <auteur>Autre</auteur>
      <date>1/01/13 11:58</date>
      <document>Menhir.html</document>
    </metadata>
    <SEval type="axe_intentionnel" idSE="3">
      <descriptive value="1" />
      <narrative value="0" />
      <explicative value="0" />
      <prescriptive value="0" />
      <procedurale value="0" />
      <argumentative value="0" />
      <intentionnel_autre value="0" />
    </SEval>
  </annotation>
  <annotation type="2">
    <metadata>
      <id>3</id>
      <auteur>Autre</auteur>
      <date>1/01/13 11:58</date>
      <document>Menhir.html</document>
    </metadata>
    <SEval type="axe_semantique" idSE="3">
      <visee_ontologique value="1">
        <isA value="1" />
        <partOf value="0" />
        <instanceOf value="0" />
        <ontologique_autre value="0" />
      </visee_ontologique>
      <metalinguistique value="0">
        <hyperonymie value="0" />
        <meronymie value="0" />
        <homonymie value="0" />
        <synonymie value="0" />
        <multilingue value="0" />
        <lexical_autre value="0" />
      </metalinguistique>
      <semantique_autre value="0" />
      <contextuelle value="0" />
    </SEval>
  </annotation>
  <annotation type="2">
    <metadata>
      <id>4</id>
      <auteur>Autre</auteur>
      <date>1/01/13 12:00</date>
      <document>Menhir.html</document>
    </metadata>
    <SEval type="axe_visuel" idSE="4">
      <horizontale value="1" />
      <verticale value="0" />
      <navigationnelle value="0" />
      <hypertextuelle value="1" />
    </SEval>
  </annotation>
  <annotation type="2">
    <metadata>
      <id>4</id>
      <auteur>Autre</auteur>
      <date>1/01/13 12:00</date>
      <document>Menhir.html</document>
    </metadata>
    <SEval type="axe_rhetorique" idSE="4">
      <paradigmatique value="1" />
      <syntagmatique value="0" />
      <hybride value="0" />
      <bivalente value="0" />
    </SEval>
  </annotation>
  <annotation type="2">
    <metadata>
      <id>4</id>
      <auteur>Autre</auteur>
      <date>1/01/13 12:00</date>
      <document>Menhir.html</document>
    </metadata>
    <SEval type="axe_intentionnel" idSE="4">
      <descriptive value="1" />
      <narrative value="0" />
      <explicative value="0" />
      <prescriptive value="0" />
      <procedurale value="0" />
      <argumentative value="0" />
      <intentionnel_autre value="0" />
    </SEval>
  </annotation>
  <annotation type="2">
    <metadata>
      <id>4</id>
      <auteur>Autre</auteur>
      <date>1/01/13 12:00</date>
      <document>Menhir.html</document>
    </metadata>
    <SEval type="axe_semantique" idSE="4">
      <visee_ontologique value="1">
        <isA value="0" />
        <partOf value="1" />
        <instanceOf value="0" />
        <ontologique_autre value="0" />
      </visee_ontologique>
      <metalinguistique value="0">
        <hyperonymie value="0" />
        <meronymie value="0" />
        <homonymie value="0" />
        <synonymie value="0" />
        <multilingue value="0" />
        <lexical_autre value="0" />
      </metalinguistique>
      <semantique_autre value="0" />
      <contextuelle value="1" />
    </SEval>
  </annotation>
  <annotation type="2">
    <metadata>
      <id>5</id>
      <auteur>Autre</auteur>
      <date>1/01/13 12:01</date>
      <document>Menhir.html</document>
    </metadata>
    <SEval type="axe_visuel" idSE="5">
      <horizontale value="1" />
      <verticale value="0" />
      <navigationnelle value="0" />
      <hypertextuelle value="1" />
    </SEval>
  </annotation>
  <annotation type="2">
    <metadata>
      <id>5</id>
      <auteur>Autre</auteur>
      <date>1/01/13 12:01</date>
      <document>Menhir.html</document>
    </metadata>
    <SEval type="axe_rhetorique" idSE="5">
      <paradigmatique value="1" />
      <syntagmatique value="0" />
      <hybride value="0" />
      <bivalente value="0" />
    </SEval>
  </annotation>
  <annotation type="2">
    <metadata>
      <id>5</id>
      <auteur>Autre</auteur>
      <date>1/01/13 12:01</date>
      <document>Menhir.html</document>
    </metadata>
    <SEval type="axe_intentionnel" idSE="5">
      <descriptive value="1" />
      <narrative value="0" />
      <explicative value="0" />
      <prescriptive value="0" />
      <procedurale value="0" />
      <argumentative value="0" />
      <intentionnel_autre value="0" />
    </SEval>
  </annotation>
  <annotation type="2">
    <metadata>
      <id>5</id>
      <auteur>Autre</auteur>
      <date>1/01/13 12:01</date>
      <document>Menhir.html</document>
    </metadata>
    <SEval type="axe_semantique" idSE="5">
      <visee_ontologique value="1">
        <isA value="0" />
        <partOf value="1" />
        <instanceOf value="0" />
        <ontologique_autre value="0" />
      </visee_ontologique>
      <metalinguistique value="0">
        <hyperonymie value="0" />
        <meronymie value="0" />
        <homonymie value="0" />
        <synonymie value="0" />
        <multilingue value="0" />
        <lexical_autre value="0" />
      </metalinguistique>
      <semantique_autre value="0" />
      <contextuelle value="1" />
    </SEval>
  </annotation>
  <annotation type="2">
    <metadata>
      <id>6</id>
      <auteur>Autre</auteur>
      <date>1/01/13 12:02</date>
      <document>Menhir.html</document>
    </metadata>
    <SEval type="axe_visuel" idSE="6">
      <horizontale value="1" />
      <verticale value="0" />
      <navigationnelle value="0" />
      <hypertextuelle value="1" />
    </SEval>
  </annotation>
  <annotation type="2">
    <metadata>
      <id>6</id>
      <auteur>Autre</auteur>
      <date>1/01/13 12:02</date>
      <document>Menhir.html</document>
    </metadata>
    <SEval type="axe_rhetorique" idSE="6">
      <paradigmatique value="1" />
      <syntagmatique value="0" />
      <hybride value="0" />
      <bivalente value="0" />
    </SEval>
  </annotation>
  <annotation type="2">
    <metadata>
      <id>6</id>
      <auteur>Autre</auteur>
      <date>1/01/13 12:02</date>
      <document>Menhir.html</document>
    </metadata>
    <SEval type="axe_intentionnel" idSE="6">
      <descriptive value="1" />
      <narrative value="0" />
      <explicative value="0" />
      <prescriptive value="0" />
      <procedurale value="0" />
      <argumentative value="0" />
      <intentionnel_autre value="0" />
    </SEval>
  </annotation>
  <annotation type="2">
    <metadata>
      <id>6</id>
      <auteur>Autre</auteur>
      <date>1/01/13 12:02</date>
      <document>Menhir.html</document>
    </metadata>
    <SEval type="axe_semantique" idSE="6">
      <visee_ontologique value="1">
        <isA value="0" />
        <partOf value="1" />
        <instanceOf value="0" />
        <ontologique_autre value="0" />
      </visee_ontologique>
      <metalinguistique value="0">
        <hyperonymie value="0" />
        <meronymie value="0" />
        <homonymie value="0" />
        <synonymie value="0" />
        <multilingue value="0" />
        <lexical_autre value="0" />
      </metalinguistique>
      <semantique_autre value="0" />
      <contextuelle value="1" />
    </SEval>
  </annotation>
  <annotation type="2">
    <metadata>
      <id>7</id>
      <auteur>Autre</auteur>
      <date>8/01/13 13:04</date>
      <document>Menhir.html</document>
    </metadata>
    <SEval type="axe_visuel" idSE="7">
      <horizontale value="1" />
      <verticale value="0" />
      <navigationnelle value="0" />
      <hypertextuelle value="1" />
    </SEval>
  </annotation>
  <annotation type="2">
    <metadata>
      <id>7</id>
      <auteur>Autre</auteur>
      <date>8/01/13 13:04</date>
      <document>Menhir.html</document>
    </metadata>
    <SEval type="axe_rhetorique" idSE="7">
      <paradigmatique value="1" />
      <syntagmatique value="0" />
      <hybride value="0" />
      <bivalente value="0" />
    </SEval>
  </annotation>
  <annotation type="2">
    <metadata>
      <id>7</id>
      <auteur>Autre</auteur>
      <date>8/01/13 13:04</date>
      <document>Menhir.html</document>
    </metadata>
    <SEval type="axe_intentionnel" idSE="7">
      <descriptive value="1" />
      <narrative value="0" />
      <explicative value="0" />
      <prescriptive value="0" />
      <procedurale value="0" />
      <argumentative value="0" />
      <intentionnel_autre value="0" />
    </SEval>
  </annotation>
  <annotation type="2">
    <metadata>
      <id>7</id>
      <auteur>Autre</auteur>
      <date>8/01/13 13:04</date>
      <document>Menhir.html</document>
    </metadata>
    <SEval type="axe_semantique" idSE="7">
      <visee_ontologique value="1">
        <isA value="0" />
        <partOf value="1" />
        <instanceOf value="0" />
        <ontologique_autre value="0" />
      </visee_ontologique>
      <metalinguistique value="0">
        <hyperonymie value="0" />
        <meronymie value="0" />
        <homonymie value="0" />
        <synonymie value="0" />
        <multilingue value="0" />
        <lexical_autre value="0" />
      </metalinguistique>
      <semantique_autre value="0" />
      <contextuelle value="1" />
    </SEval>
  </annotation>
  <annotation type="2">
    <metadata>
      <id>8</id>
      <auteur>Autre</auteur>
      <date>1/01/13 12:03</date>
      <document>Menhir.html</document>
    </metadata>
    <SEval type="axe_visuel" idSE="8">
      <horizontale value="1" />
      <verticale value="0" />
      <navigationnelle value="0" />
      <hypertextuelle value="1" />
    </SEval>
  </annotation>
  <annotation type="2">
    <metadata>
      <id>8</id>
      <auteur>Autre</auteur>
      <date>1/01/13 12:03</date>
      <document>Menhir.html</document>
    </metadata>
    <SEval type="axe_rhetorique" idSE="8">
      <paradigmatique value="1" />
      <syntagmatique value="0" />
      <hybride value="0" />
      <bivalente value="0" />
    </SEval>
  </annotation>
  <annotation type="2">
    <metadata>
      <id>8</id>
      <auteur>Autre</auteur>
      <date>1/01/13 12:03</date>
      <document>Menhir.html</document>
    </metadata>
    <SEval type="axe_intentionnel" idSE="8">
      <descriptive value="1" />
      <narrative value="0" />
      <explicative value="0" />
      <prescriptive value="0" />
      <procedurale value="0" />
      <argumentative value="0" />
      <intentionnel_autre value="0" />
    </SEval>
  </annotation>
  <annotation type="2">
    <metadata>
      <id>8</id>
      <auteur>Autre</auteur>
      <date>1/01/13 12:03</date>
      <document>Menhir.html</document>
    </metadata>
    <SEval type="axe_semantique" idSE="8">
      <visee_ontologique value="1">
        <isA value="0" />
        <partOf value="1" />
        <instanceOf value="0" />
        <ontologique_autre value="0" />
      </visee_ontologique>
      <metalinguistique value="0">
        <hyperonymie value="0" />
        <meronymie value="0" />
        <homonymie value="0" />
        <synonymie value="0" />
        <multilingue value="0" />
        <lexical_autre value="0" />
      </metalinguistique>
      <semantique_autre value="0" />
      <contextuelle value="0" />
    </SEval>
  </annotation>
</root>
